{
  "kind": "collectionType",
  "collectionName": "categories",
  "info": {
    "singularName": "category",
    "pluralName": "categories",
    "displayName": "Categories",
    "description": ""
  },
  "options": {
    "draftAndPublish": true
  },
  "pluginOptions": {},
  "attributes": {
    "name": {
      "type": "string"
    },
    "games": {
      "type": "relation",
      "relation": "manyToMany",
      "target": "api::game.game",
      "mappedBy": "categories"
    },
    "colour": {
      "type": "string"
    }
  }
}
